transphrase/__init__.py
transphrase/__main__.py
transphrase/api/__init__.py
transphrase/api/handler.py
transphrase/cache/__init__.py
transphrase/cache/context_cache.py
transphrase/cache/language_constants.py
transphrase/cache/series_context.py
transphrase/cache/translation_cache.py
transphrase/cli/__init__.py
transphrase/cli/cli.py
transphrase/cli/series_manager.py
transphrase/core/__init__.py
transphrase/core/config.py
transphrase/core/config_manager.py
transphrase/core/config_validator.py
transphrase/core/container.py
transphrase/core/context_tracker.py
transphrase/core/db/__init__.py
transphrase/core/db/db_operations.py
transphrase/core/processing/__init__.py
transphrase/core/processing/chunk_processor.py
transphrase/core/processing/file_handlers.py
transphrase/core/processing/file_processor.py
transphrase/core/processing/html_processor.py
transphrase/core/processing/main_processor.py
transphrase/core/processing/progress_tracker.py
transphrase/core/processing/text_processor.py
transphrase/core/quality/__init__.py
transphrase/core/quality/quality_assessor.py
transphrase/core/utils/language_detector.py
transphrase/database/__init__.py
transphrase/database/models.py
transphrase/formats/html/__init__.py
transphrase/formats/html/html_entities.py
transphrase/formats/html/html_extractor.py
transphrase/formats/html/html_protection.py
transphrase/formats/html/html_rebuilder.py
transphrase/formats/html/html_validation.py
transphrase/plugins/__init__.py
transphrase/plugins/plugin_manager.py
transphrase/plugins/plugin_setup.py
transphrase/rate_limiting/__init__.py
transphrase/rate_limiting/rate_limiter.py
transphrase/ui/__init__.py
transphrase/ui/model_selector.py
transphrase-0.1.5.dist-info/METADATA
transphrase-0.1.5.dist-info/WHEEL
transphrase-0.1.5.dist-info/entry_points.txt
transphrase-0.1.5.dist-info/licenses/LICENSE
transphrase-0.1.5.dist-info/RECORD
