Metadata-Version: 2.4
Name: transphrase
Version: 0.1.5
Summary: AI-powered web novel translation tool
Project-URL: Homepage, https://github.com/shinyPy/TransPhrase
Project-URL: Issues, https://github.com/shinyPy/TransPhrase/issues
Project-URL: Documentation, https://github.com/shinyPy/TransPhrase#readme
Project-URL: Source, https://github.com/shinyPy/TransPhrase
Author-email: shinyPy <adveniscool@gmail.com>
License: MIT
License-File: LICENSE
Classifier: License :: OSI Approved :: MIT License
Classifier: Operating System :: OS Independent
Classifier: Programming Language :: Python :: 3
Requires-Python: >=3.9
Requires-Dist: beautifulsoup4>=4.12.2
Requires-Dist: ebooklib>=0.18
Requires-Dist: langdetect>=1.0.9
Requires-Dist: lxml>=5.4.0
Requires-Dist: openai>=1.70.0
Requires-Dist: pyyaml>=6.0.2
Requires-Dist: readchar>=4.2.1
Requires-Dist: rich>=14.0.0
Requires-Dist: sqlalchemy>=2.0.40
Requires-Dist: tenacity>=9.1.0
